{
    "Sections": [
        {
            "Section name": "t2_s5_r4",
            "Type": 0,
            "Number of players": 135,
            "Number of teams": 10,
            "Rounds paired": 3,
            "Rounds played": 3,
            "Regular": true,
            "Rapid": false,
            "Blitz": false,
            "Acceleration": 0,
            "Use team pairings": true,
            "Team cut": 4,
            "Players": [
                {
                    "Pair number": 1,
                    "Name": "Chen, Wenyong",
                    "Rating": 1596,
                    "Results": [
                        "X;54;B",
                        "+;41;W",
                        "-;40;B"
                    ]
                },
                {
                    "Pair number": 2,
                    "Name": "Ganapatiraju, Sree C",
                    "Rating": 1591,
                    "Results": [
                        "+;86;B",
                        "+;66;W",
                        "=;46;B"
                    ]
                },
                {
                    "Pair number": 3,
                    "Name": "Malcolm, Barringto",
                    "Rating": 1589,
                    "Results": [
                        "+;57;W",
                        "+;44;B",
                        "+;47;W"
                    ]
                },
                {
                    "Pair number": 4,
                    "Name": "Bershanskiy, Vladi",
                    "Rating": 1584,
                    "Results": [
                        "=;58;B",
                        "+;72;W",
                        "-;132;B"
                    ]
                },
                {
                    "Pair number": 5,
                    "Name": "Palacherla, Nithin",
                    "Rating": 1583,
                    "Results": [
                        "+;87;W",
                        "+;68;B",
                        "=;73;W"
                    ]
                },
                {
                    "Pair number": 6,
                    "Name": "Effland, Nicholas Alan",
                    "Rating": 1582,
                    "Results": [
                        "-;90;B",
                        "-;96;W",
                        "+;92;B"
                    ]
                },
                {
                    "Pair number": 7,
                    "Name": "Chanadiri, Avtandil",
                    "Rating": 1579,
                    "Results": [
                        "+;95;W",
                        "-;97;B",
                        "+;69;W"
                    ]
                },
                {
                    "Pair number": 8,
                    "Name": "Mack, Tyshaune",
                    "Rating": 1577,
                    "Results": [
                        "+;61;W",
                        "-;47;B",
                        "-;75;W"
                    ]
                },
                {
                    "Pair number": 9,
                    "Name": "Overlingas, Akeras",
                    "Rating": 1575,
                    "Results": [
                        "+;80;W",
                        "+;51;B",
                        "+;77;W"
                    ]
                },
                {
                    "Pair number": 10,
                    "Name": "Hamilton, Jack",
                    "Rating": 1573,
                    "Results": [
                        "-;63;B",
                        "-;67;W",
                        "-;87;W"
                    ]
                },
                {
                    "Pair number": 11,
                    "Name": "Bowman, Robert J",
                    "Rating": 1569,
                    "Results": [
                        "-;64;W",
                        "-;79;B",
                        "+;95;W"
                    ]
                },
                {
                    "Pair number": 12,
                    "Name": "Botnik, Benjamin A",
                    "Rating": 1568,
                    "Results": [
                        "+;65;B",
                        "+;45;W",
                        "-;63;B"
                    ]
                },
                {
                    "Pair number": 13,
                    "Name": "Bellia, Robert",
                    "Rating": 1567,
                    "Team": "RENBEL",
                    "Results": [
                        "+;67;W",
                        "+;64;B",
                        "=;97;W"
                    ]
                },
                {
                    "Pair number": 14,
                    "Name": "Harris, Isaac Lott",
                    "Rating": 1561,
                    "Results": [
                        "-;73;W",
                        "+;84;B",
                        "+;79;W"
                    ]
                },
                {
                    "Pair number": 15,
                    "Name": "Warren, Lamar",
                    "Rating": 1561,
                    "Results": [
                        "=;72;B",
                        "+;85;W",
                        "-;62;B"
                    ]
                },
                {
                    "Pair number": 16,
                    "Name": "Lin, Haoyi",
                    "Rating": 1557,
                    "Results": [
                        "-;76;B",
                        "+;78;W",
                        "=;70;B"
                    ]
                },
                {
                    "Pair number": 17,
                    "Name": "Walker, Edwin",
                    "Rating": 1555,
                    "Results": [
                        "-;77;W",
                        "=;104;B",
                        "+;83;W"
                    ]
                },
                {
                    "Pair number": 18,
                    "Name": "Koo, Benjamin",
                    "Rating": 1553,
                    "Results": [
                        "+;79;W",
                        "-;73;B",
                        "+;88;W"
                    ]
                },
                {
                    "Pair number": 19,
                    "Name": "Muhammad, L.C.",
                    "Rating": 1553,
                    "Results": [
                        "+;78;B",
                        "-;63;W",
                        "+;74;B"
                    ]
                },
                {
                    "Pair number": 20,
                    "Name": "Prasad, Amit",
                    "Rating": 1552,
                    "Results": [
                        "+;96;B",
                        "+;74;W",
                        "-;81;B"
                    ]
                },
                {
                    "Pair number": 21,
                    "Name": "Prasanna, Kevin Fr",
                    "Rating": 1552,
                    "Results": [
                        "+;83;B",
                        "-;110;W",
                        "=;76;B"
                    ]
                },
                {
                    "Pair number": 22,
                    "Name": "Andrews, Chris R",
                    "Rating": 1551,
                    "Results": [
                        "H;-1;-",
                        "H;-1;-",
                        "-;82;B"
                    ]
                },
                {
                    "Pair number": 23,
                    "Name": "Valderrama, Atom",
                    "Rating": 1551,
                    "Results": [
                        "-;97;W",
                        "+;103;B",
                        "-;89;W"
                    ]
                },
                {
                    "Pair number": 24,
                    "Name": "Rajan, Rajanish",
                    "Rating": 1548,
                    "Results": [
                        "+;84;W",
                        "-;77;B",
                        "-;107;W"
                    ]
                },
                {
                    "Pair number": 25,
                    "Name": "Kuo, Aaron",
                    "Rating": 1547,
                    "Results": [
                        "+;92;B",
                        "-;116;W",
                        "-;90;B"
                    ]
                },
                {
                    "Pair number": 26,
                    "Name": "Jiang, Stephen Y",
                    "Rating": 1546,
                    "Results": [
                        "=;94;W",
                        "=;88;B",
                        "+;109;W"
                    ]
                },
                {
                    "Pair number": 27,
                    "Name": "Qu, Brian",
                    "Rating": 1546,
                    "Results": [
                        "=;98;B",
                        "-;132;W",
                        "-;85;B"
                    ]
                },
                {
                    "Pair number": 28,
                    "Name": "Schwartz, Ilan Sam",
                    "Rating": 1542,
                    "Results": [
                        "X;93;B",
                        "+;76;W",
                        "-;99;B"
                    ]
                },
                {
                    "Pair number": 29,
                    "Name": "Bell Jr, Daniel A",
                    "Rating": 1541,
                    "Results": [
                        "-;99;W",
                        "-;109;B",
                        "=;102;B"
                    ]
                },
                {
                    "Pair number": 30,
                    "Name": "Zhuge, Katherine",
                    "Rating": 1540,
                    "Results": [
                        "+;101;B",
                        "+;118;W",
                        "=;110;B"
                    ]
                },
                {
                    "Pair number": 31,
                    "Name": "Koh, Bennett",
                    "Rating": 1539,
                    "Results": [
                        "+;104;W",
                        "-;99;B",
                        "+;112;W"
                    ]
                },
                {
                    "Pair number": 32,
                    "Name": "Stinson, Russell",
                    "Rating": 1539,
                    "Results": [
                        "=;106;B",
                        "+;100;W",
                        "=;71;B"
                    ]
                },
                {
                    "Pair number": 33,
                    "Name": "Jolly, Brad",
                    "Rating": 1535,
                    "Results": [
                        "+;103;W",
                        "-;114;B",
                        "+;121;W"
                    ]
                },
                {
                    "Pair number": 34,
                    "Name": "Casares, Marcos Gabriel",
                    "Rating": 1533,
                    "Results": [
                        "+;105;B",
                        "+;90;W",
                        "-;116;B"
                    ]
                },
                {
                    "Pair number": 35,
                    "Name": "Sharf, Sam",
                    "Rating": 1533,
                    "Team": "SHAPIN",
                    "Results": [
                        "+;102;W",
                        "=;62;B",
                        "+;124;W"
                    ]
                },
                {
                    "Pair number": 36,
                    "Name": "Lozano Jr, Rodolf",
                    "Rating": 1532,
                    "Results": [
                        "+;109;W",
                        "+;112;B",
                        "=;114;W"
                    ]
                },
                {
                    "Pair number": 37,
                    "Name": "Abed, Hashim",
                    "Rating": 1528,
                    "Results": [
                        "B;0;-",
                        "+;115;W",
                        "+;129;B"
                    ]
                },
                {
                    "Pair number": 38,
                    "Name": "Sharma, Abdd",
                    "Rating": 1527,
                    "Results": [
                        "-;110;B",
                        "=;83;W",
                        "=;98;B"
                    ]
                },
                {
                    "Pair number": 39,
                    "Name": "Angell, Walter Wil",
                    "Rating": 1526,
                    "Results": [
                        "-;112;W",
                        "=;113;B",
                        "=;100;B"
                    ]
                },
                {
                    "Pair number": 40,
                    "Name": "Przybyl, Michael J",
                    "Rating": 1526,
                    "Results": [
                        "+;111;B",
                        "+;130;W",
                        "+;1;W"
                    ]
                },
                {
                    "Pair number": 41,
                    "Name": "Divver, Cassius Ju",
                    "Rating": 1525,
                    "Results": [
                        "+;113;W",
                        "-;1;B",
                        "=;125;W"
                    ]
                },
                {
                    "Pair number": 42,
                    "Name": "Ayala, Juan Bosco",
                    "Rating": 1524,
                    "Results": [
                        "-;116;B",
                        "+;92;W",
                        "+;91;B"
                    ]
                },
                {
                    "Pair number": 43,
                    "Name": "DebMisra, Ariv",
                    "Rating": 1523,
                    "Results": [
                        "-;118;B",
                        "=;101;W",
                        "-;122;B"
                    ]
                },
                {
                    "Pair number": 44,
                    "Name": "Fleming, Angelo V",
                    "Rating": 1523,
                    "Results": [
                        "+;117;W",
                        "-;3;W",
                        "+;96;B"
                    ]
                },
                {
                    "Pair number": 45,
                    "Name": "Alowitz, Arthur L",
                    "Rating": 1518,
                    "Results": [
                        "+;120;W",
                        "-;12;B",
                        "-;127;W"
                    ]
                },
                {
                    "Pair number": 46,
                    "Name": "Luo, Leon",
                    "Rating": 1517,
                    "Results": [
                        "+;107;W",
                        "+;121;B",
                        "=;2;W"
                    ]
                },
                {
                    "Pair number": 47,
                    "Name": "Stricker II, Paul",
                    "Rating": 1516,
                    "Results": [
                        "+;122;B",
                        "+;8;W",
                        "-;3;B"
                    ]
                },
                {
                    "Pair number": 48,
                    "Name": "Devalapalli, Prana",
                    "Rating": 1514,
                    "Results": [
                        "H;-1;-",
                        "-;94;B",
                        "=;104;W"
                    ]
                },
                {
                    "Pair number": 49,
                    "Name": "Sanders II, Ronald",
                    "Rating": 1513,
                    "Results": [
                        "H;0;-",
                        "=;126;W",
                        "-;106;B"
                    ]
                },
                {
                    "Pair number": 50,
                    "Name": "Covey, Theodore",
                    "Rating": 1511,
                    "Results": [
                        "-;81;B",
                        "-;91;W",
                        "H;-1;-"
                    ]
                },
                {
                    "Pair number": 51,
                    "Name": "Elwell, Jake",
                    "Rating": 1508,
                    "Results": [
                        "+;89;W",
                        "-;9;W",
                        "+;108;B"
                    ]
                },
                {
                    "Pair number": 52,
                    "Name": "Krayn, Aaron Samuel",
                    "Rating": 1506,
                    "Results": [
                        "+;108;B",
                        "-;129;W",
                        "+;115;B"
                    ]
                },
                {
                    "Pair number": 53,
                    "Name": "Lyle, Luke",
                    "Rating": 1506,
                    "Results": [
                        "=;124;W",
                        "+;128;B",
                        "-;94;W"
                    ]
                },
                {
                    "Pair number": 54,
                    "Name": "Bankston, Charles",
                    "Rating": 1500,
                    "Results": [
                        "F;1;W",
                        "U;0;-",
                        "U;0;-"
                    ]
                },
                {
                    "Pair number": 55,
                    "Name": "Lebon, John A",
                    "Rating": 1500,
                    "Results": [
                        "-;114;W",
                        "-;107;B",
                        "+;103;W"
                    ]
                },
                {
                    "Pair number": 56,
                    "Name": "Millenbach, Lew A",
                    "Rating": 1500,
                    "Results": [
                        "-;130;B",
                        "+;111;W",
                        "=;117;B"
                    ]
                },
                {
                    "Pair number": 57,
                    "Name": "Dobbs, Namir",
                    "Rating": 1498,
                    "Results": [
                        "-;3;B",
                        "-;117;W",
                        "U;0;-"
                    ]
                },
                {
                    "Pair number": 58,
                    "Name": "Hardaway, Noni",
                    "Rating": 1496,
                    "Results": [
                        "=;4;W",
                        "-;124;B",
                        "+;113;W"
                    ]
                },
                {
                    "Pair number": 59,
                    "Name": "Clibanoff, Matthew",
                    "Rating": 1493,
                    "Results": [
                        "F;115;B",
                        "U;0;-",
                        "U;0;-"
                    ]
                },
                {
                    "Pair number": 60,
                    "Name": "Pham, Linda",
                    "Rating": 1493,
                    "Team": "PHALE",
                    "Results": [
                        "H;-1;-",
                        "=;106;W",
                        "=;118;B"
                    ]
                },
                {
                    "Pair number": 61,
                    "Name": "Ying, Katherine We",
                    "Rating": 1493,
                    "Results": [
                        "-;8;B",
                        "=;122;W",
                        "-;101;B"
                    ]
                },
                {
                    "Pair number": 62,
                    "Name": "Moore, Adam",
                    "Rating": 1489,
                    "Results": [
                        "+;91;B",
                        "=;35;W",
                        "+;15;W"
                    ]
                },
                {
                    "Pair number": 63,
                    "Name": "Drath IV, Wilfred",
                    "Rating": 1488,
                    "Team": "RAPDRA",
                    "Results": [
                        "+;10;W",
                        "+;19;B",
                        "+;12;W"
                    ]
                },
                {
                    "Pair number": 64,
                    "Name": "Robertson, Wade",
                    "Rating": 1488,
                    "Results": [
                        "+;11;B",
                        "-;13;W",
                        "=;126;B"
                    ]
                },
                {
                    "Pair number": 65,
                    "Name": "Li, Emma Shurong",
                    "Rating": 1487,
                    "Team": "LILI",
                    "Results": [
                        "-;12;W",
                        "+;120;B",
                        "+;131;W"
                    ]
                },
                {
                    "Pair number": 66,
                    "Name": "Feldman, Michael Gregory",
                    "Rating": 1484,
                    "Results": [
                        "+;119;W",
                        "-;2;B",
                        "=;130;W"
                    ]
                },
                {
                    "Pair number": 67,
                    "Name": "Burak, Rachel",
                    "Rating": 1483,
                    "Team": "BURRAY",
                    "Results": [
                        "-;13;B",
                        "+;10;B",
                        "+;105;W"
                    ]
                },
                {
                    "Pair number": 68,
                    "Name": "Jones, Alvin R",
                    "Rating": 1482,
                    "Results": [
                        "+;123;B",
                        "-;5;W",
                        "+;133;B"
                    ]
                },
                {
                    "Pair number": 69,
                    "Name": "Oyekole, Oyekola",
                    "Rating": 1479,
                    "Results": [
                        "-;121;W",
                        "+;119;B",
                        "-;7;B"
                    ]
                },
                {
                    "Pair number": 70,
                    "Name": "Thandra, Samanyu",
                    "Rating": 1473,
                    "Results": [
                        "=;125;W",
                        "=;131;B",
                        "=;16;W"
                    ]
                },
                {
                    "Pair number": 71,
                    "Name": "Zhou, Derek",
                    "Rating": 1472,
                    "Results": [
                        "=;126;B",
                        "+;98;W",
                        "=;32;W"
                    ]
                },
                {
                    "Pair number": 72,
                    "Name": "Hayes, Richard Tho",
                    "Rating": 1468,
                    "Results": [
                        "=;15;W",
                        "-;4;B",
                        "-;128;W"
                    ]
                },
                {
                    "Pair number": 73,
                    "Name": "Ma, Jin",
                    "Rating": 1465,
                    "Results": [
                        "+;14;B",
                        "+;18;W",
                        "=;5;B"
                    ]
                },
                {
                    "Pair number": 74,
                    "Name": "Misra, Aritra Kuma",
                    "Rating": 1465,
                    "Results": [
                        "+;127;W",
                        "-;20;B",
                        "-;19;W"
                    ]
                },
                {
                    "Pair number": 75,
                    "Name": "Manivannan, Prajit",
                    "Rating": 1464,
                    "Results": [
                        "-;129;B",
                        "+;105;W",
                        "+;8;B"
                    ]
                },
                {
                    "Pair number": 76,
                    "Name": "Ren, Stanley",
                    "Rating": 1463,
                    "Results": [
                        "+;16;W",
                        "-;28;B",
                        "=;21;W"
                    ]
                },
                {
                    "Pair number": 77,
                    "Name": "Li, Sophie",
                    "Rating": 1462,
                    "Team": "LIZHA",
                    "Results": [
                        "+;17;B",
                        "+;24;W",
                        "-;9;B"
                    ]
                },
                {
                    "Pair number": 78,
                    "Name": "Lopez III, Ralph A",
                    "Rating": 1461,
                    "Results": [
                        "-;19;W",
                        "-;16;B",
                        "-;119;W"
                    ]
                },
                {
                    "Pair number": 79,
                    "Name": "Sinkar, Anagha Ani",
                    "Rating": 1460,
                    "Team": "SINSIN",
                    "Results": [
                        "-;18;B",
                        "+;11;W",
                        "-;14;B"
                    ]
                },
                {
                    "Pair number": 80,
                    "Name": "Wade, Robert D",
                    "Rating": 1458,
                    "Results": [
                        "-;9;B",
                        "-;81;W",
                        "+;111;B"
                    ]
                },
                {
                    "Pair number": 81,
                    "Name": "Eggleston, Jack",
                    "Rating": 1457,
                    "Results": [
                        "+;50;W",
                        "+;80;B",
                        "+;20;W"
                    ]
                },
                {
                    "Pair number": 82,
                    "Name": "Hill, Christopher",
                    "Rating": 1450,
                    "Results": [
                        "=;131;W",
                        "=;125;B",
                        "+;22;W"
                    ]
                },
                {
                    "Pair number": 83,
                    "Name": "North, John B",
                    "Rating": 1445,
                    "Results": [
                        "-;21;W",
                        "=;38;B",
                        "-;17;B"
                    ]
                },
                {
                    "Pair number": 84,
                    "Name": "Chambers, Marty",
                    "Rating": 1442,
                    "Results": [
                        "-;24;B",
                        "-;14;W",
                        "U;0;-"
                    ]
                },
                {
                    "Pair number": 85,
                    "Name": "Wang, Boyan",
                    "Rating": 1442,
                    "Results": [
                        "H;-1;-",
                        "-;15;B",
                        "+;27;W"
                    ]
                },
                {
                    "Pair number": 86,
                    "Name": "Tyau, David",
                    "Rating": 1438,
                    "Results": [
                        "-;2;W",
                        "-;127;B",
                        "+;120;W"
                    ]
                },
                {
                    "Pair number": 87,
                    "Name": "Harrilal, Kevin Guyah",
                    "Rating": 1434,
                    "Results": [
                        "-;5;B",
                        "-;108;W",
                        "+;10;B"
                    ]
                },
                {
                    "Pair number": 88,
                    "Name": "Zhu, Sophie",
                    "Rating": 1429,
                    "Results": [
                        "H;-1;-",
                        "=;26;W",
                        "-;18;B"
                    ]
                },
                {
                    "Pair number": 89,
                    "Name": "DeDona, Christopher",
                    "Rating": 1428,
                    "Results": [
                        "-;51;B",
                        "+;102;W",
                        "+;23;B"
                    ]
                },
                {
                    "Pair number": 90,
                    "Name": "Kumar, Varun",
                    "Rating": 1428,
                    "Results": [
                        "+;6;W",
                        "-;34;B",
                        "+;25;W"
                    ]
                },
                {
                    "Pair number": 91,
                    "Name": "Weiss, Matthew David",
                    "Rating": 1426,
                    "Results": [
                        "-;62;W",
                        "+;50;B",
                        "-;42;W"
                    ]
                },
                {
                    "Pair number": 92,
                    "Name": "Delgado, Edwin G",
                    "Rating": 1418,
                    "Results": [
                        "-;25;W",
                        "-;42;B",
                        "-;6;W"
                    ]
                },
                {
                    "Pair number": 93,
                    "Name": "Arvind, Charithra",
                    "Rating": 1413,
                    "Results": [
                        "F;28;W",
                        "U;0;-",
                        "U;0;-"
                    ]
                },
                {
                    "Pair number": 94,
                    "Name": "Kunapuli, Pranav T",
                    "Rating": 1413,
                    "Results": [
                        "=;26;B",
                        "+;48;W",
                        "+;53;B"
                    ]
                },
                {
                    "Pair number": 95,
                    "Name": "Shirbroun, David W",
                    "Rating": 1410,
                    "Results": [
                        "-;7;B",
                        "-;123;W",
                        "-;11;B"
                    ]
                },
                {
                    "Pair number": 96,
                    "Name": "Paxson, Alexander Edwin",
                    "Rating": 1409,
                    "Results": [
                        "-;20;W",
                        "+;6;B",
                        "-;44;W"
                    ]
                },
                {
                    "Pair number": 97,
                    "Name": "Stuckert, Elena",
                    "Rating": 1408,
                    "Results": [
                        "+;23;B",
                        "+;7;W",
                        "=;13;B"
                    ]
                },
                {
                    "Pair number": 98,
                    "Name": "Leonard, Navek",
                    "Rating": 1407,
                    "Results": [
                        "=;27;W",
                        "-;71;B",
                        "=;38;W"
                    ]
                },
                {
                    "Pair number": 99,
                    "Name": "Nagarajan, Prabhat",
                    "Rating": 1407,
                    "Results": [
                        "+;29;B",
                        "+;31;W",
                        "+;28;W"
                    ]
                },
                {
                    "Pair number": 100,
                    "Name": "Tippa, Aswath Sris",
                    "Rating": 1406,
                    "Results": [
                        "H;-1;-",
                        "-;32;B",
                        "=;39;W"
                    ]
                },
                {
                    "Pair number": 101,
                    "Name": "Krishnan, Mihika",
                    "Rating": 1404,
                    "Team": "KRIKRI",
                    "Results": [
                        "-;30;W",
                        "=;43;B",
                        "+;61;W"
                    ]
                },
                {
                    "Pair number": 102,
                    "Name": "Harris, Clarence",
                    "Rating": 1400,
                    "Results": [
                        "-;35;B",
                        "-;89;B",
                        "=;29;W"
                    ]
                },
                {
                    "Pair number": 103,
                    "Name": "Rempe, Lennik",
                    "Rating": 1400,
                    "Results": [
                        "-;33;B",
                        "-;23;W",
                        "-;55;B"
                    ]
                },
                {
                    "Pair number": 104,
                    "Name": "Tichacek, Jerome W",
                    "Rating": 1400,
                    "Results": [
                        "-;31;B",
                        "=;17;W",
                        "=;48;B"
                    ]
                },
                {
                    "Pair number": 105,
                    "Name": "Pu, Ethan",
                    "Rating": 1397,
                    "Results": [
                        "-;34;W",
                        "-;75;B",
                        "-;67;B"
                    ]
                },
                {
                    "Pair number": 106,
                    "Name": "Bao, James",
                    "Rating": 1393,
                    "Results": [
                        "=;32;W",
                        "=;60;B",
                        "+;49;W"
                    ]
                },
                {
                    "Pair number": 107,
                    "Name": "Zeigler, Nathan",
                    "Rating": 1375,
                    "Results": [
                        "-;46;B",
                        "+;55;W",
                        "+;24;B"
                    ]
                },
                {
                    "Pair number": 108,
                    "Name": "Sun, Yimeng",
                    "Rating": 1372,
                    "Results": [
                        "-;52;W",
                        "+;87;B",
                        "-;51;W"
                    ]
                },
                {
                    "Pair number": 109,
                    "Name": "Uthaman, Abhinav",
                    "Rating": 1359,
                    "Results": [
                        "-;36;B",
                        "+;29;W",
                        "-;26;B"
                    ]
                },
                {
                    "Pair number": 110,
                    "Name": "Meyers, Evan",
                    "Rating": 1353,
                    "Results": [
                        "+;38;W",
                        "+;21;B",
                        "=;30;W"
                    ]
                },
                {
                    "Pair number": 111,
                    "Name": "Chapman, Joshua",
                    "Rating": 1333,
                    "Results": [
                        "-;40;W",
                        "-;56;B",
                        "-;80;W"
                    ]
                },
                {
                    "Pair number": 112,
                    "Name": "Gu, Thomas",
                    "Rating": 1333,
                    "Results": [
                        "+;39;B",
                        "-;36;W",
                        "-;31;B"
                    ]
                },
                {
                    "Pair number": 113,
                    "Name": "Fan, Shenghan",
                    "Rating": 1330,
                    "Results": [
                        "-;41;B",
                        "=;39;W",
                        "-;58;B"
                    ]
                },
                {
                    "Pair number": 114,
                    "Name": "Weingarten, Phineas Hugo",
                    "Rating": 1324,
                    "Results": [
                        "+;55;B",
                        "+;33;W",
                        "=;36;B"
                    ]
                },
                {
                    "Pair number": 115,
                    "Name": "Tebelman, Kyle",
                    "Rating": 1320,
                    "Results": [
                        "X;59;W",
                        "-;37;B",
                        "-;52;W"
                    ]
                },
                {
                    "Pair number": 116,
                    "Name": "Nino, Wilson",
                    "Rating": 1318,
                    "Results": [
                        "+;42;W",
                        "+;25;B",
                        "+;34;W"
                    ]
                },
                {
                    "Pair number": 117,
                    "Name": "Desai, Esha",
                    "Rating": 1310,
                    "Team": "DESDES",
                    "Results": [
                        "-;44;B",
                        "+;57;B",
                        "=;56;W"
                    ]
                },
                {
                    "Pair number": 118,
                    "Name": "Laido, Matthew",
                    "Rating": 1305,
                    "Results": [
                        "+;43;W",
                        "-;30;B",
                        "=;60;W"
                    ]
                },
                {
                    "Pair number": 119,
                    "Name": "Smith, Graham Bradley",
                    "Rating": 1304,
                    "Results": [
                        "-;66;B",
                        "-;69;W",
                        "+;78;B"
                    ]
                },
                {
                    "Pair number": 120,
                    "Name": "Li, Christian Y",
                    "Rating": 1299,
                    "Results": [
                        "-;45;B",
                        "-;65;W",
                        "-;86;B"
                    ]
                },
                {
                    "Pair number": 121,
                    "Name": "Liu, Enmon Benjami",
                    "Rating": 1296,
                    "Results": [
                        "+;69;B",
                        "-;46;W",
                        "-;33;B"
                    ]
                },
                {
                    "Pair number": 122,
                    "Name": "Zhang, Sean Xiaoan",
                    "Rating": 1290,
                    "Results": [
                        "-;47;W",
                        "=;61;B",
                        "+;43;W"
                    ]
                },
                {
                    "Pair number": 123,
                    "Name": "Chang, Leonhard",
                    "Rating": 1286,
                    "Results": [
                        "-;68;W",
                        "+;95;B",
                        "H;-1;-"
                    ]
                },
                {
                    "Pair number": 124,
                    "Name": "Nallabothula, Vine",
                    "Rating": 1281,
                    "Results": [
                        "=;53;B",
                        "+;58;W",
                        "-;35;B"
                    ]
                },
                {
                    "Pair number": 125,
                    "Name": "Senthil, Rahul Srinivaas",
                    "Rating": 1272,
                    "Results": [
                        "=;70;B",
                        "=;82;W",
                        "=;41;B"
                    ]
                },
                {
                    "Pair number": 126,
                    "Name": "Davis, Zackary",
                    "Rating": 1259,
                    "Results": [
                        "=;71;W",
                        "=;49;B",
                        "=;64;W"
                    ]
                },
                {
                    "Pair number": 127,
                    "Name": "Sripada, Anisha",
                    "Rating": 1220,
                    "Results": [
                        "-;74;B",
                        "+;86;W",
                        "+;45;B"
                    ]
                },
                {
                    "Pair number": 128,
                    "Name": "Liu, Kevin",
                    "Rating": 1218,
                    "Results": [
                        "H;-1;-",
                        "-;53;W",
                        "+;72;B"
                    ]
                },
                {
                    "Pair number": 129,
                    "Name": "Wei, Robert Fanjun",
                    "Rating": 1210,
                    "Results": [
                        "+;75;W",
                        "+;52;B",
                        "-;37;W"
                    ]
                },
                {
                    "Pair number": 130,
                    "Name": "Desai, Ajay",
                    "Rating": 1179,
                    "Results": [
                        "+;56;W",
                        "-;40;B",
                        "=;66;B"
                    ]
                },
                {
                    "Pair number": 131,
                    "Name": "Bharathy Mohan, Aarav Sai",
                    "Rating": 1142,
                    "Results": [
                        "=;82;B",
                        "=;70;W",
                        "-;65;B"
                    ]
                },
                {
                    "Pair number": 132,
                    "Name": "Mott, Cooper",
                    "Rating": 1104,
                    "Results": [
                        "B;-1;-",
                        "+;27;B",
                        "+;4;W"
                    ]
                },
                {
                    "Pair number": 133,
                    "Name": "Force, Wyeth",
                    "Rating": 1049,
                    "Results": [
                        "-;135;B",
                        "B;-1;-",
                        "-;68;W"
                    ]
                },
                {
                    "Pair number": 134,
                    "Name": "Bangaru, Sahishn",
                    "Rating": 1003,
                    "Results": [
                        "H;0;-",
                        "H;0;-",
                        "H;0;-"
                    ]
                },
                {
                    "Pair number": 135,
                    "Name": "Wang, Winston Huan",
                    "Rating": 931,
                    "Results": [
                        "+;133;W",
                        "U;0;-",
                        "U;0;-"
                    ]
                }
            ],
            "Teams": [
                {
                    "Pair number": 1,
                    "Full name": "RENBEL",
                    "Team code": "RENBEL"
                },
                {
                    "Pair number": 2,
                    "Full name": "SHAPIN",
                    "Team code": "SHAPIN"
                },
                {
                    "Pair number": 3,
                    "Full name": "PHALE",
                    "Team code": "PHALE"
                },
                {
                    "Pair number": 4,
                    "Full name": "RAPDRA",
                    "Team code": "RAPDRA"
                },
                {
                    "Pair number": 5,
                    "Full name": "LILI",
                    "Team code": "LILI"
                },
                {
                    "Pair number": 6,
                    "Full name": "BURRAY",
                    "Team code": "BURRAY"
                },
                {
                    "Pair number": 7,
                    "Full name": "LIZHA",
                    "Team code": "LIZHA"
                },
                {
                    "Pair number": 8,
                    "Full name": "SINSIN",
                    "Team code": "SINSIN"
                },
                {
                    "Pair number": 9,
                    "Full name": "KRIKRI",
                    "Team code": "KRIKRI"
                },
                {
                    "Pair number": 10,
                    "Full name": "DESDES",
                    "Team code": "DESDES"
                }
            ],
            "Byes": [
                {
                    "Pair number": 22,
                    "Round": 1,
                    "Points": 0.5
                },
                {
                    "Pair number": 22,
                    "Round": 2,
                    "Points": 0.5
                },
                {
                    "Pair number": 37,
                    "Round": 1,
                    "Points": 1
                },
                {
                    "Pair number": 48,
                    "Round": 1,
                    "Points": 0.5
                },
                {
                    "Pair number": 49,
                    "Round": 1,
                    "Points": 0.5
                },
                {
                    "Pair number": 50,
                    "Round": 3,
                    "Points": 0.5
                },
                {
                    "Pair number": 53,
                    "Round": 4,
                    "Points": 0.5
                },
                {
                    "Pair number": 60,
                    "Round": 1,
                    "Points": 0.5
                },
                {
                    "Pair number": 85,
                    "Round": 1,
                    "Points": 0.5
                },
                {
                    "Pair number": 88,
                    "Round": 1,
                    "Points": 0.5
                },
                {
                    "Pair number": 90,
                    "Round": 5,
                    "Points": 0.5
                },
                {
                    "Pair number": 96,
                    "Round": 5,
                    "Points": 0.5
                },
                {
                    "Pair number": 100,
                    "Round": 1,
                    "Points": 0.5
                },
                {
                    "Pair number": 123,
                    "Round": 3,
                    "Points": 0.5
                },
                {
                    "Pair number": 123,
                    "Round": 4,
                    "Points": 0.5
                },
                {
                    "Pair number": 123,
                    "Round": 5,
                    "Points": 0.5
                },
                {
                    "Pair number": 128,
                    "Round": 1,
                    "Points": 0.5
                },
                {
                    "Pair number": 132,
                    "Round": 1,
                    "Points": 1
                },
                {
                    "Pair number": 133,
                    "Round": 2,
                    "Points": 1
                },
                {
                    "Pair number": 134,
                    "Round": 1,
                    "Points": 0.5
                },
                {
                    "Pair number": 134,
                    "Round": 2,
                    "Points": 0.5
                },
                {
                    "Pair number": 134,
                    "Round": 3,
                    "Points": 0.5
                }
            ],
            "Withdrawals": [
                {
                    "Pair number": 4,
                    "Rounds withdrawn": [
                        4,
                        5
                    ]
                },
                {
                    "Pair number": 8,
                    "Rounds withdrawn": [
                        5
                    ]
                },
                {
                    "Pair number": 21,
                    "Rounds withdrawn": [
                        4,
                        5
                    ]
                },
                {
                    "Pair number": 23,
                    "Rounds withdrawn": [
                        4,
                        5
                    ]
                },
                {
                    "Pair number": 25,
                    "Rounds withdrawn": [
                        4,
                        5
                    ]
                },
                {
                    "Pair number": 33,
                    "Rounds withdrawn": [
                        5
                    ]
                },
                {
                    "Pair number": 43,
                    "Rounds withdrawn": [
                        4,
                        5
                    ]
                },
                {
                    "Pair number": 49,
                    "Rounds withdrawn": [
                        4,
                        5
                    ]
                },
                {
                    "Pair number": 54,
                    "Rounds withdrawn": [
                        2,
                        3,
                        4,
                        5
                    ]
                },
                {
                    "Pair number": 57,
                    "Rounds withdrawn": [
                        3,
                        4,
                        5
                    ]
                },
                {
                    "Pair number": 59,
                    "Rounds withdrawn": [
                        2,
                        3,
                        4,
                        5
                    ]
                },
                {
                    "Pair number": 69,
                    "Rounds withdrawn": [
                        4,
                        5
                    ]
                },
                {
                    "Pair number": 84,
                    "Rounds withdrawn": [
                        3,
                        4,
                        5
                    ]
                },
                {
                    "Pair number": 85,
                    "Rounds withdrawn": [
                        5
                    ]
                },
                {
                    "Pair number": 86,
                    "Rounds withdrawn": [
                        4,
                        5
                    ]
                },
                {
                    "Pair number": 93,
                    "Rounds withdrawn": [
                        2,
                        3,
                        4,
                        5
                    ]
                },
                {
                    "Pair number": 111,
                    "Rounds withdrawn": [
                        4,
                        5
                    ]
                },
                {
                    "Pair number": 135,
                    "Rounds withdrawn": [
                        2,
                        3,
                        4,
                        5
                    ]
                }
            ]
        }
    ]
}